kltpicker
