Metadata-Version: 2.1
Name: kltpicker
Version: 1.2.6
Summary: KLT picker
Home-page: https://github.com/ShkolniskyLab/kltpicker
Author: Dalit Cohen
Author-email: dalitcohen@mail.tau.ac.il
License: GNU General Public License v3.0
Platform: UNKNOWN
Requires-Python: ~=3.6
Provides-Extra: gpu
